CHANGELOG.md
LICENCE.txt
MANIFEST.in
README.md
setup.cfg
setup.py
django_plugins_bihealth.egg-info/PKG-INFO
django_plugins_bihealth.egg-info/SOURCES.txt
django_plugins_bihealth.egg-info/dependency_links.txt
django_plugins_bihealth.egg-info/not-zip-safe
django_plugins_bihealth.egg-info/requires.txt
django_plugins_bihealth.egg-info/top_level.txt
djangoplugins/__init__.py
djangoplugins/admin.py
djangoplugins/apps.py
djangoplugins/fields.py
djangoplugins/models.py
djangoplugins/point.py
djangoplugins/signals.py
djangoplugins/tests.py
djangoplugins/utils.py
djangoplugins/management/__init__.py
djangoplugins/management/commands/__init__.py
djangoplugins/management/commands/syncplugins.py
djangoplugins/migrations/0001_initial.py
djangoplugins/migrations/0002_auto_20230718_1254.py
djangoplugins/migrations/__init__.py
djangoplugins/templatetags/__init__.py
djangoplugins/templatetags/plugins.py